[
	{
		"anonymous": false,
		"inputs": [
			{
				"indexed": true,
				"internalType": "address",
				"name": "instance",
				"type": "address"
			},
			{
				"indexed": true,
				"internalType": "address",
				"name": "provider",
				"type": "address"
			}
		],
		"name": "Created",
		"type": "event"
	},
	{
		"inputs": [
			{
				"internalType": "address",
				"name": "owner",
				"type": "address"
			}
		],
		"name": "count",
		"outputs": [
			{
				"internalType": "uint256",
				"name": "",
				"type": "uint256"
			}
		],
		"stateMutability": "view",
		"type": "function"
	},
	{
		"inputs": [
			{
				"internalType": "address",
				"name": "provider",
				"type": "address"
			},
			{
				"internalType": "uint256",
				"name": "reserveBalance",
				"type": "uint256"
			},
			{
				"internalType": "address[]",
				"name": "recipients",
				"type": "address[]"
			},
			{
				"internalType": "uint256[]",
				"name": "bips",
				"type": "uint256[]"
			},
			{
				"internalType": "bool[]",
				"name": "wrap",
				"type": "bool[]"
			},
			{
				"internalType": "bool",
				"name": "editable",
				"type": "bool"
			},
			{
				"internalType": "string",
				"name": "description",
				"type": "string"
			}
		],
		"name": "create",
		"outputs": [
			{
				"internalType": "address",
				"name": "instance",
				"type": "address"
			}
		],
		"stateMutability": "nonpayable",
		"type": "function"
	},
	{
		"inputs": [
			{
				"internalType": "address",
				"name": "owner",
				"type": "address"
			},
			{
				"internalType": "uint256",
				"name": "i",
				"type": "uint256"
			}
		],
		"name": "get",
		"outputs": [
			{
				"internalType": "address",
				"name": "instance",
				"type": "address"
			},
			{
				"internalType": "string",
				"name": "description",
				"type": "string"
			}
		],
		"stateMutability": "view",
		"type": "function"
	},
	{
		"inputs": [
			{
				"internalType": "address",
				"name": "owner",
				"type": "address"
			}
		],
		"name": "getAll",
		"outputs": [
			{
				"components": [
					{
						"internalType": "address",
						"name": "instance",
						"type": "address"
					},
					{
						"internalType": "string",
						"name": "description",
						"type": "string"
					}
				],
				"internalType": "struct IRewardDistributorFactory.NamedInstance[]",
				"name": "",
				"type": "tuple[]"
			}
		],
		"stateMutability": "view",
		"type": "function"
	},
	{
		"inputs": [
			{
				"internalType": "address",
				"name": "instance",
				"type": "address"
			}
		],
		"name": "remove",
		"outputs": [],
		"stateMutability": "nonpayable",
		"type": "function"
	},
	{
		"inputs": [
			{
				"internalType": "address",
				"name": "instance",
				"type": "address"
			},
			{
				"internalType": "string",
				"name": "description",
				"type": "string"
			}
		],
		"name": "rename",
		"outputs": [],
		"stateMutability": "nonpayable",
		"type": "function"
	}
]